setup.py
iv_backend/__init__.py
iv_backend/iv_one_python.py
iv_one.egg-info/PKG-INFO
iv_one.egg-info/SOURCES.txt
iv_one.egg-info/dependency_links.txt
iv_one.egg-info/requires.txt
iv_one.egg-info/top_level.txt