Metadata-Version: 2.1
Name: iv-one
Version: 1.0.1
Summary: This package can be used tocompare databases and generate reports.
Home-page: https://example.com
Author: Chris Topalidis
Author-email: c.topalidis@iv-one.nl
License: MIT
Keywords: report,database,comparison
Classifier: Development Status :: 3 - Alpha
Classifier: Intended Audience :: Developers
Classifier: Topic :: Software Development :: Build Tools
Classifier: License :: OSI Approved :: MIT License
Classifier: Programming Language :: Python :: 3.8
Classifier: Programming Language :: Python :: 3.9
Classifier: Programming Language :: Python :: 3.10
Classifier: Programming Language :: Python :: 3.11
